ptr.py
pytest_runner-5.0.dist-info/LICENSE
pytest_runner-5.0.dist-info/METADATA
pytest_runner-5.0.dist-info/WHEEL
pytest_runner-5.0.dist-info/entry_points.txt
pytest_runner-5.0.dist-info/top_level.txt
pytest_runner-5.0.dist-info/RECORD
